<?xml version="1.0" encoding="utf-8"?>
<package name="libcurl3-gnutls" section="libs">
    <description>
        <summary>easy-to-use client-side URL transfer library (GnuTLS flavour)</summary>
        <p>
        libcurl is an easy-to-use client-side URL transfer library, supporting DICT,
        FILE, FTP, FTPS, GOPHER, HTTP, HTTPS, IMAP, IMAPS, LDAP, LDAPS, POP3, POP3S,
        RTMP, RTSP, SCP, SFTP, SMTP, SMTPS, TELNET and TFTP.
        </p>
        <p>
        libcurl supports SSL certificates, HTTP POST, HTTP PUT, FTP uploading, HTTP
        form based upload, proxies, cookies, user+password authentication (Basic,
        Digest, NTLM, Negotiate, Kerberos), file transfer resume, http proxy tunneling
        and more!
        </p>
        <p>
        libcurl is free, thread-safe, IPv6 compatible, feature rich, well supported,
        fast, thoroughly documented and is already used by many known, big and
        successful companies and numerous applications.
        </p>
        <p>
        SSL support is provided by GnuTLS.
        </p>
    </description>

    <contents subdir="gnutls">
        <file src="${prefix}/lib/libcurl-gnutls.so.*"/>
    </contents>
</package>
