<?xml version="1.0" encoding="utf-8"?>
<package name="busybox-ipsvd-symlinks" section="admin">
    <description>
        <summary>Substitutes for (some) programs from the ipsvd package</summary>
        <p>
            This package contains the symbolic links for the following applets:
        </p>
        <ul>
            <li>tcpsvd</li>
            <li>udpsvd</li>
        </ul>
    </description>

    <requires>
        <package name="busybox"/>
    </requires>

    <provides>
        <package name="ipsvd"/>
    </provides>

    <conflicts>
        <package name="ipsvd"/>
    </conflicts>

    <replaces>
        <package name="ipsvd"/>
    </replaces>

    <contents>
        <file src="${prefix}/bin/tcpsvd"/>
        <file src="${prefix}/bin/udpsvd"/>
    </contents>
</package>
